Metadata-Version: 2.1
Name: NODEFit
Version: 0.1
Summary: Fit time-series data with a Neural Differential Equation
Home-page: https://github.com/gpavanb1/NODEFit
Author: gpavanb1
Author-email: gpavanb@gmail.com
License: MIT
Project-URL: Bug Reports, https://github.com/gpavanb1/NODEFit/issues
Project-URL: Source, https://github.com/gpavanb1/NODEFit/
Keywords: python neural-network pytorch numerical-methods neural-ode
Platform: UNKNOWN
Classifier: Topic :: Scientific/Engineering :: Mathematics
Classifier: License :: OSI Approved :: MIT License
Classifier: Programming Language :: Python :: 3
Classifier: Programming Language :: Python :: 3.6
Classifier: Programming Language :: Python :: 3.7
Classifier: Programming Language :: Python :: 3 :: Only
